devserver/__init__.py
devserver/cli/__init__.py
devserver/cli/config.py
devserver/cli/main.py
devserver/cli/ssh_config.py
devserver/cli/utils.py
devserver/cli/handlers/__init__.py
devserver/cli/handlers/create.py
devserver/cli/handlers/delete.py
devserver/cli/handlers/describe.py
devserver/cli/handlers/list.py
devserver/cli/handlers/ssh.py
devserver/cli/handlers/ssh_proxy.py
devserver/cli/handlers/user.py
devserver/crds/__init__.py
devserver/crds/base.py
devserver/crds/const.py
devserver/crds/devserver.py
devserver/operator/__init__.py
devserver/operator/operator.py
devserver/operator/devserver/__init__.py
devserver/operator/devserver/handler.py
devserver/operator/devserver/host_keys.py
devserver/operator/devserver/lifecycle.py
devserver/operator/devserver/reconciler.py
devserver/operator/devserver/validation.py
devserver/operator/devserver/resources/__init__.py
devserver/operator/devserver/resources/configmap.py
devserver/operator/devserver/resources/services.py
devserver/operator/devserver/resources/statefulset.py
devserver/operator/devserverflavor/handler.py
devserver/operator/devserveruser/__init__.py
devserver/operator/devserveruser/handler.py
devserver/operator/devserveruser/rbac.py
devserver/operator/devserveruser/reconciler.py
devserver/utils/__init__.py
devserver/utils/flavors.py
devserver/utils/network.py
devserver/utils/time.py
devserver/utils/users.py
devserver_operator-0.0.1.dist-info/licenses/LICENSE
devserver_operator-0.0.1.dist-info/METADATA
devserver_operator-0.0.1.dist-info/WHEEL
devserver_operator-0.0.1.dist-info/entry_points.txt
devserver_operator-0.0.1.dist-info/top_level.txt
devserver_operator-0.0.1.dist-info/RECORD
