Metadata-Version: 2.4
Name: devserver-operator
Version: 0.0.1
Summary: A Kubernetes operator for dev servers.
Author-email: Your Name <you@example.com>
Project-URL: Homepage, https://github.com/pypa/sampleproject
Project-URL: Issues, https://github.com/pypa/sampleproject/issues
Classifier: Programming Language :: Python :: 3
Classifier: License :: OSI Approved :: Apache Software License
Classifier: Operating System :: OS Independent
Requires-Python: >=3.9
License-File: LICENSE
Requires-Dist: kopf>=1.37.0
Requires-Dist: kubernetes>=28.1.0
Requires-Dist: rich
Requires-Dist: click>=8.0
Requires-Dist: PyYAML>=6.0.1
Dynamic: license-file
